Verilog/cla_adder_struct.v
`timescale 1ns/1ps

module my_and(A,B,Y);
    input A,B;
    output Y;
    assign Y = A & B;
endmodule

module my_not(A,Y);
    input A;
    output Y;
    assign Y = ~A;
endmodule

module my_or(A,B,Y);
    input A,B;
    output Y;
    assign Y = A | B;
endmodule

module my_xor(A,B,Y);
    input A,B;
    output Y;
    assign Y = A^B;
endmodule

module my_nand(A,B,Y);
    input A,B;
    output Y;
    assign Y = ~(A & B);
endmodule

module dff(clk,d,q);
    input clk;
    input d;
    output q;
    my_not not_gate(d,d_not);
    my_nand g1(d,clk,s_bar);
    my_nand g2(d_not,clk,r_bar);
    my_nand g3(s_bar,q_not,q);
    my_nand g4(r_bar,q, q_not);
endmodule

module adder(A_in, B_in, Cin, sum, Cout,clk);
    input clk;
    input [3:0]A_in, B_in;
    input Cin;
    output [3:0]sum;
    output Cout;

    wire [3:0] A, B;
    wire P0, P1, P2, P3;
    wire G0, G1, G2, G3;
    wire C1, C2, C3;
    wire pc0, p1p0c0, p1g0, p2p1p0c0, p2p1g0, p2g1, p3p2p1p0c0, p3p2p1g0, p3p2g1, p3g2;

    dff ff1(clk,A_in[0],A[0]);
    dff ff2(clk,A_in[1],A[1]);
    dff ff3(clk,A_in[2],A[2]);
    dff ff4(clk,A_in[3],A[3]);

    dff ff5(clk,B_in[0],B[0]);
    dff ff6(clk,B_in[1],B[1]);
    dff ff7(clk,B_in[2],B[2]);
    dff ff8(clk,B_in[3],B[3]);

    
    my_xor g1(A[0], B[0],P0);
    my_xor g2(A[1], B[1],P1);
    my_xor g3(A[2], B[2],P2);
    my_xor g4(A[3], B[3],P3);

    my_and g5(A[0], B[0], G0);
    my_and g6(A[1], B[1], G1);
    my_and g7(A[2], B[2], G2);
    my_and g8(A[3], B[3], G3);

    my_and g9(P0,Cin,pc0);
    my_or g10(pc0, G0,C1);

    and g11(p1p0c0, P1, P0, Cin);
    and g12(p1g0, P1, G0);
    or g13(C2,p1p0c0, p1g0, G1);

    and g14(p2p1p0c0, P2, P1, P0, Cin);
    and g15(p2p1g0, P2, P1, G0);
    and g16(p2g1,P2, G1);
    or g17(C3, p2p1p0c0, p2p1g0, p2g1, G2);

    wire Cout_out;
    wire [3:0]sum_out;

    and g18(p3p2p1p0c0, P3, P2, P1, P0, Cin);
    and g19(p3p2p1g0, P3, P2, P1, G0);
    and g20(p3p2g1, P3, P2, G1);
    and g21(p3g2, P3, G2);
    or g22(Cout_out, p3p2p1p0c0, p3p2p1g0, p3p2g1, p3g2, G3);

    my_xor g23(P0, Cin, sum_out[0]);
    my_xor g24(P1, C1, sum_out[1]);
    my_xor g25(P2, C2, sum_out[2]);
    my_xor g26(P3, C3, sum_out[3]);

    dff ff9(clk,sum_out[0],sum[0]);
    dff ff10(clk,sum_out[1],sum[1]);
    dff ff11(clk,sum_out[2],sum[2]);
    dff ff12(clk,sum_out[3],sum[3]);
    dff ff13(clk, Cout_out,Cout);

endmodule

module tb();

reg [3:0] A,B;
reg Cin;
reg clk;

wire [3:0] sum;
wire Cout;
integer i;

adder dut(.A_in(A),.B_in(B),.Cout(Cout),.sum(sum),.Cin(Cin),.clk(clk));

initial begin
    A = 4'b0;
    B = 4'b0;
    Cin = 1'b0;
end

initial begin 
    clk = 0;
    forever #5 clk = ~clk;
end

initial begin 
    for(i = 0; i< 16 ; i = i+1)
    begin
        A = i;
        B = i;
        Cin = 0;
        #10;
    end
end

initial begin
    $monitor($time, " A = %4b , B = %4b , Cin = %b , Sum = %4b , Cout = %b, Clk : ", A, B, Cin, sum, Cout,clk);
    #160;
    $finish;
end

initial begin
    $dumpfile("cla_adder.vcd");
    $dumpvars(0,tb);
end
endmodule

Verilog/cla_adder.vcd
$date
	Wed Dec  4 15:59:18 2024
$end
$version
	Icarus Verilog
$end
$timescale
	1ps
$end
$scope module tb $end
$var wire 4 ! sum [3:0] $end
$var wire 1 " Cout $end
$var reg 4 # A [3:0] $end
$var reg 4 $ B [3:0] $end
$var reg 1 % Cin $end
$var reg 1 & clk $end
$var integer 32 ' i [31:0] $end
$scope module dut $end
$var wire 4 ( A_in [3:0] $end
$var wire 4 ) B_in [3:0] $end
$var wire 1 * C2 $end
$var wire 1 + C3 $end
$var wire 1 % Cin $end
$var wire 1 , Cout_out $end
$var wire 1 & clk $end
$var wire 1 - p1g0 $end
$var wire 1 . p1p0c0 $end
$var wire 1 / p2g1 $end
$var wire 1 0 p2p1g0 $end
$var wire 1 1 p2p1p0c0 $end
$var wire 1 2 p3g2 $end
$var wire 1 3 p3p2g1 $end
$var wire 1 4 p3p2p1g0 $end
$var wire 1 5 p3p2p1p0c0 $end
$var wire 4 6 sum_out [3:0] $end
$var wire 4 7 sum [3:0] $end
$var wire 1 8 pc0 $end
$var wire 1 9 P3 $end
$var wire 1 : P2 $end
$var wire 1 ; P1 $end
$var wire 1 < P0 $end
$var wire 1 = G3 $end
$var wire 1 > G2 $end
$var wire 1 ? G1 $end
$var wire 1 @ G0 $end
$var wire 1 " Cout $end
$var wire 1 A C1 $end
$var wire 4 B B [3:0] $end
$var wire 4 C A [3:0] $end
$scope module ff1 $end
$var wire 1 & clk $end
$var wire 1 D d $end
$var wire 1 E s_bar $end
$var wire 1 F r_bar $end
$var wire 1 G q_not $end
$var wire 1 H q $end
$var wire 1 I d_not $end
$scope module g1 $end
$var wire 1 D A $end
$var wire 1 & B $end
$var wire 1 E Y $end
$upscope $end
$scope module g2 $end
$var wire 1 & B $end
$var wire 1 F Y $end
$var wire 1 I A $end
$upscope $end
$scope module g3 $end
$var wire 1 E A $end
$var wire 1 H Y $end
$var wire 1 G B $end
$upscope $end
$scope module g4 $end
$var wire 1 F A $end
$var wire 1 H B $end
$var wire 1 G Y $end
$upscope $end
$scope module not_gate $end
$var wire 1 D A $end
$var wire 1 I Y $end
$upscope $end
$upscope $end
$scope module ff10 $end
$var wire 1 & clk $end
$var wire 1 J d $end
$var wire 1 K s_bar $end
$var wire 1 L r_bar $end
$var wire 1 M q_not $end
$var wire 1 N q $end
$var wire 1 O d_not $end
$scope module g1 $end
$var wire 1 J A $end
$var wire 1 & B $end
$var wire 1 K Y $end
$upscope $end
$scope module g2 $end
$var wire 1 & B $end
$var wire 1 L Y $end
$var wire 1 O A $end
$upscope $end
$scope module g3 $end
$var wire 1 K A $end
$var wire 1 N Y $end
$var wire 1 M B $end
$upscope $end
$scope module g4 $end
$var wire 1 L A $end
$var wire 1 N B $end
$var wire 1 M Y $end
$upscope $end
$scope module not_gate $end
$var wire 1 J A $end
$var wire 1 O Y $end
$upscope $end
$upscope $end
$scope module ff11 $end
$var wire 1 & clk $end
$var wire 1 P d $end
$var wire 1 Q s_bar $end
$var wire 1 R r_bar $end
$var wire 1 S q_not $end
$var wire 1 T q $end
$var wire 1 U d_not $end
$scope module g1 $end
$var wire 1 P A $end
$var wire 1 & B $end
$var wire 1 Q Y $end
$upscope $end
$scope module g2 $end
$var wire 1 & B $end
$var wire 1 R Y $end
$var wire 1 U A $end
$upscope $end
$scope module g3 $end
$var wire 1 Q A $end
$var wire 1 T Y $end
$var wire 1 S B $end
$upscope $end
$scope module g4 $end
$var wire 1 R A $end
$var wire 1 T B $end
$var wire 1 S Y $end
$upscope $end
$scope module not_gate $end
$var wire 1 P A $end
$var wire 1 U Y $end
$upscope $end
$upscope $end
$scope module ff12 $end
$var wire 1 & clk $end
$var wire 1 V d $end
$var wire 1 W s_bar $end
$var wire 1 X r_bar $end
$var wire 1 Y q_not $end
$var wire 1 Z q $end
$var wire 1 [ d_not $end
$scope module g1 $end
$var wire 1 V A $end
$var wire 1 & B $end
$var wire 1 W Y $end
$upscope $end
$scope module g2 $end
$var wire 1 & B $end
$var wire 1 X Y $end
$var wire 1 [ A $end
$upscope $end
$scope module g3 $end
$var wire 1 W A $end
$var wire 1 Z Y $end
$var wire 1 Y B $end
$upscope $end
$scope module g4 $end
$var wire 1 X A $end
$var wire 1 Z B $end
$var wire 1 Y Y $end
$upscope $end
$scope module not_gate $end
$var wire 1 V A $end
$var wire 1 [ Y $end
$upscope $end
$upscope $end
$scope module ff13 $end
$var wire 1 & clk $end
$var wire 1 , d $end
$var wire 1 \ s_bar $end
$var wire 1 ] r_bar $end
$var wire 1 ^ q_not $end
$var wire 1 " q $end
$var wire 1 _ d_not $end
$scope module g1 $end
$var wire 1 , A $end
$var wire 1 & B $end
$var wire 1 \ Y $end
$upscope $end
$scope module g2 $end
$var wire 1 & B $end
$var wire 1 ] Y $end
$var wire 1 _ A $end
$upscope $end
$scope module g3 $end
$var wire 1 \ A $end
$var wire 1 " Y $end
$var wire 1 ^ B $end
$upscope $end
$scope module g4 $end
$var wire 1 ] A $end
$var wire 1 " B $end
$var wire 1 ^ Y $end
$upscope $end
$scope module not_gate $end
$var wire 1 , A $end
$var wire 1 _ Y $end
$upscope $end
$upscope $end
$scope module ff2 $end
$var wire 1 & clk $end
$var wire 1 ` d $end
$var wire 1 a s_bar $end
$var wire 1 b r_bar $end
$var wire 1 c q_not $end
$var wire 1 d q $end
$var wire 1 e d_not $end
$scope module g1 $end
$var wire 1 ` A $end
$var wire 1 & B $end
$var wire 1 a Y $end
$upscope $end
$scope module g2 $end
$var wire 1 & B $end
$var wire 1 b Y $end
$var wire 1 e A $end
$upscope $end
$scope module g3 $end
$var wire 1 a A $end
$var wire 1 d Y $end
$var wire 1 c B $end
$upscope $end
$scope module g4 $end
$var wire 1 b A $end
$var wire 1 d B $end
$var wire 1 c Y $end
$upscope $end
$scope module not_gate $end
$var wire 1 ` A $end
$var wire 1 e Y $end
$upscope $end
$upscope $end
$scope module ff3 $end
$var wire 1 & clk $end
$var wire 1 f d $end
$var wire 1 g s_bar $end
$var wire 1 h r_bar $end
$var wire 1 i q_not $end
$var wire 1 j q $end
$var wire 1 k d_not $end
$scope module g1 $end
$var wire 1 f A $end
$var wire 1 & B $end
$var wire 1 g Y $end
$upscope $end
$scope module g2 $end
$var wire 1 & B $end
$var wire 1 h Y $end
$var wire 1 k A $end
$upscope $end
$scope module g3 $end
$var wire 1 g A $end
$var wire 1 j Y $end
$var wire 1 i B $end
$upscope $end
$scope module g4 $end
$var wire 1 h A $end
$var wire 1 j B $end
$var wire 1 i Y $end
$upscope $end
$scope module not_gate $end
$var wire 1 f A $end
$var wire 1 k Y $end
$upscope $end
$upscope $end
$scope module ff4 $end
$var wire 1 & clk $end
$var wire 1 l d $end
$var wire 1 m s_bar $end
$var wire 1 n r_bar $end
$var wire 1 o q_not $end
$var wire 1 p q $end
$var wire 1 q d_not $end
$scope module g1 $end
$var wire 1 l A $end
$var wire 1 & B $end
$var wire 1 m Y $end
$upscope $end
$scope module g2 $end
$var wire 1 & B $end
$var wire 1 n Y $end
$var wire 1 q A $end
$upscope $end
$scope module g3 $end
$var wire 1 m A $end
$var wire 1 p Y $end
$var wire 1 o B $end
$upscope $end
$scope module g4 $end
$var wire 1 n A $end
$var wire 1 p B $end
$var wire 1 o Y $end
$upscope $end
$scope module not_gate $end
$var wire 1 l A $end
$var wire 1 q Y $end
$upscope $end
$upscope $end
$scope module ff5 $end
$var wire 1 & clk $end
$var wire 1 r d $end
$var wire 1 s s_bar $end
$var wire 1 t r_bar $end
$var wire 1 u q_not $end
$var wire 1 v q $end
$var wire 1 w d_not $end
$scope module g1 $end
$var wire 1 r A $end
$var wire 1 & B $end
$var wire 1 s Y $end
$upscope $end
$scope module g2 $end
$var wire 1 & B $end
$var wire 1 t Y $end
$var wire 1 w A $end
$upscope $end
$scope module g3 $end
$var wire 1 s A $end
$var wire 1 v Y $end
$var wire 1 u B $end
$upscope $end
$scope module g4 $end
$var wire 1 t A $end
$var wire 1 v B $end
$var wire 1 u Y $end
$upscope $end
$scope module not_gate $end
$var wire 1 r A $end
$var wire 1 w Y $end
$upscope $end
$upscope $end
$scope module ff6 $end
$var wire 1 & clk $end
$var wire 1 x d $end
$var wire 1 y s_bar $end
$var wire 1 z r_bar $end
$var wire 1 { q_not $end
$var wire 1 | q $end
$var wire 1 } d_not $end
$scope module g1 $end
$var wire 1 x A $end
$var wire 1 & B $end
$var wire 1 y Y $end
$upscope $end
$scope module g2 $end
$var wire 1 & B $end
$var wire 1 z Y $end
$var wire 1 } A $end
$upscope $end
$scope module g3 $end
$var wire 1 y A $end
$var wire 1 | Y $end
$var wire 1 { B $end
$upscope $end
$scope module g4 $end
$var wire 1 z A $end
$var wire 1 | B $end
$var wire 1 { Y $end
$upscope $end
$scope module not_gate $end
$var wire 1 x A $end
$var wire 1 } Y $end
$upscope $end
$upscope $end
$scope module ff7 $end
$var wire 1 & clk $end
$var wire 1 ~ d $end
$var wire 1 !" s_bar $end
$var wire 1 "" r_bar $end
$var wire 1 #" q_not $end
$var wire 1 $" q $end
$var wire 1 %" d_not $end
$scope module g1 $end
$var wire 1 ~ A $end
$var wire 1 & B $end
$var wire 1 !" Y $end
$upscope $end
$scope module g2 $end
$var wire 1 & B $end
$var wire 1 "" Y $end
$var wire 1 %" A $end
$upscope $end
$scope module g3 $end
$var wire 1 !" A $end
$var wire 1 $" Y $end
$var wire 1 #" B $end
$upscope $end
$scope module g4 $end
$var wire 1 "" A $end
$var wire 1 $" B $end
$var wire 1 #" Y $end
$upscope $end
$scope module not_gate $end
$var wire 1 ~ A $end
$var wire 1 %" Y $end
$upscope $end
$upscope $end
$scope module ff8 $end
$var wire 1 & clk $end
$var wire 1 &" d $end
$var wire 1 '" s_bar $end
$var wire 1 (" r_bar $end
$var wire 1 )" q_not $end
$var wire 1 *" q $end
$var wire 1 +" d_not $end
$scope module g1 $end
$var wire 1 &" A $end
$var wire 1 & B $end
$var wire 1 '" Y $end
$upscope $end
$scope module g2 $end
$var wire 1 & B $end
$var wire 1 (" Y $end
$var wire 1 +" A $end
$upscope $end
$scope module g3 $end
$var wire 1 '" A $end
$var wire 1 *" Y $end
$var wire 1 )" B $end
$upscope $end
$scope module g4 $end
$var wire 1 (" A $end
$var wire 1 *" B $end
$var wire 1 )" Y $end
$upscope $end
$scope module not_gate $end
$var wire 1 &" A $end
$var wire 1 +" Y $end
$upscope $end
$upscope $end
$scope module ff9 $end
$var wire 1 & clk $end
$var wire 1 ," d $end
$var wire 1 -" s_bar $end
$var wire 1 ." r_bar $end
$var wire 1 /" q_not $end
$var wire 1 0" q $end
$var wire 1 1" d_not $end
$scope module g1 $end
$var wire 1 ," A $end
$var wire 1 & B $end
$var wire 1 -" Y $end
$upscope $end
$scope module g2 $end
$var wire 1 & B $end
$var wire 1 ." Y $end
$var wire 1 1" A $end
$upscope $end
$scope module g3 $end
$var wire 1 -" A $end
$var wire 1 0" Y $end
$var wire 1 /" B $end
$upscope $end
$scope module g4 $end
$var wire 1 ." A $end
$var wire 1 0" B $end
$var wire 1 /" Y $end
$upscope $end
$scope module not_gate $end
$var wire 1 ," A $end
$var wire 1 1" Y $end
$upscope $end
$upscope $end
$scope module g1 $end
$var wire 1 2" A $end
$var wire 1 3" B $end
$var wire 1 < Y $end
$upscope $end
$scope module g10 $end
$var wire 1 A Y $end
$var wire 1 @ B $end
$var wire 1 8 A $end
$upscope $end
$scope module g2 $end
$var wire 1 4" A $end
$var wire 1 5" B $end
$var wire 1 ; Y $end
$upscope $end
$scope module g23 $end
$var wire 1 < A $end
$var wire 1 % B $end
$var wire 1 6" Y $end
$upscope $end
$scope module g24 $end
$var wire 1 ; A $end
$var wire 1 A B $end
$var wire 1 7" Y $end
$upscope $end
$scope module g25 $end
$var wire 1 * B $end
$var wire 1 8" Y $end
$var wire 1 : A $end
$upscope $end
$scope module g26 $end
$var wire 1 + B $end
$var wire 1 9" Y $end
$var wire 1 9 A $end
$upscope $end
$scope module g3 $end
$var wire 1 :" A $end
$var wire 1 ;" B $end
$var wire 1 : Y $end
$upscope $end
$scope module g4 $end
$var wire 1 <" A $end
$var wire 1 =" B $end
$var wire 1 9 Y $end
$upscope $end
$scope module g5 $end
$var wire 1 >" A $end
$var wire 1 ?" B $end
$var wire 1 @ Y $end
$upscope $end
$scope module g6 $end
$var wire 1 @" A $end
$var wire 1 A" B $end
$var wire 1 ? Y $end
$upscope $end
$scope module g7 $end
$var wire 1 B" A $end
$var wire 1 C" B $end
$var wire 1 > Y $end
$upscope $end
$scope module g8 $end
$var wire 1 D" A $end
$var wire 1 E" B $end
$var wire 1 = Y $end
$upscope $end
$scope module g9 $end
$var wire 1 < A $end
$var wire 1 % B $end
$var wire 1 8 Y $end
$upscope $end
$upscope $end
$upscope $end
$enddefinitions $end
#0
$dumpvars
xE"
xD"
xC"
xB"
xA"
x@"
x?"
x>"
x="
x<"
x;"
x:"
x9"
x8"
x7"
x6"
x5"
x4"
x3"
x2"
x1"
x0"
x/"
1."
1-"
x,"
1+"
x*"
x)"
1("
1'"
0&"
1%"
x$"
x#"
1""
1!"
0~
1}
x|
x{
1z
1y
0x
1w
xv
xu
1t
1s
0r
1q
xp
xo
1n
1m
0l
1k
xj
xi
1h
1g
0f
1e
xd
xc
1b
1a
0`
x_
x^
1]
1\
x[
xZ
xY
1X
1W
xV
xU
xT
xS
1R
1Q
xP
xO
xN
xM
1L
1K
xJ
1I
xH
xG
1F
1E
0D
bx C
bx B
xA
x@
x?
x>
x=
x<
x;
x:
x9
08
bx 7
bx 6
05
x4
x3
x2
01
x0
x/
0.
x-
x,
x+
x*
b0 )
b0 (
b0 '
0&
0%
b0 $
b0 #
x"
bx !
$end
#5000
0T
0Z
0N
0"
b0 !
b0 7
00"
1S
1Y
1M
1^
1/"
1U
1[
1O
0P
0V
1_
11"
0J
08"
09"
0,
0,"
07"
0*
0+
b0 6
06"
0A
0-
0/
00
02
03
04
0<
0@
0;
0?
0:
0>
09
0=
02"
0>"
04"
0@"
0:"
0B"
0<"
0D"
03"
0?"
05"
0A"
0;"
0C"
0="
0E"
0H
0d
0j
b0 C
0p
0v
0|
0$"
b0 B
0*"
1G
1c
1i
1o
1u
1{
1#"
1)"
0F
1K
0L
1Q
0R
1W
0X
1\
0]
0b
0h
0n
0t
0z
0""
0("
1-"
0."
1&
#10000
1F
1L
1R
1X
1]
1b
1h
1n
1t
1z
1""
1("
1."
0w
0I
1r
1D
0&
b1 $
b1 )
b1 #
b1 (
b1 '
#15000
0M
b10 !
b10 7
1N
0K
0O
1J
b10 6
17"
1A
0G
0u
1@
12"
1>"
13"
1?"
b1 C
1H
b1 B
1v
0E
1L
0R
0X
0]
0b
0h
0n
0s
0z
0""
0("
0."
1&
#20000
1E
1K
1R
1X
1]
1b
1h
1n
1s
1z
1""
1("
1."
1w
0}
1I
0e
0r
1x
0D
1`
0&
b10 $
b10 )
b10 #
b10 (
b10 '
#25000
0N
1M
0S
0L
b100 !
b100 7
1T
1O
0J
0Q
07"
0U
0A
1P
0@
b100 6
18"
02"
0>"
03"
0?"
1*
0H
0c
0v
0{
1?
14"
1@"
15"
1A"
1G
b10 C
1d
1u
b10 B
1|
0F
1K
1R
0X
0]
0a
0h
0n
0t
0y
0""
0("
0."
1&
#30000
1F
1L
1Q
1X
1]
1a
1h
1n
1t
1y
1""
1("
1."
0w
0I
1r
1D
0&
b11 $
b11 )
b11 #
b11 (
b11 '
#35000
0M
b110 !
b110 7
1N
0K
0O
1J
b110 6
17"
1A
0G
0u
1@
12"
1>"
13"
1?"
b11 C
1H
b11 B
1v
0E
1L
0Q
0X
0]
0a
0h
0n
0s
0y
0""
0("
0."
1&
#40000
1E
1K
1Q
1X
1]
1a
1h
1n
1s
1y
1""
1("
1."
1w
1}
0%"
1I
1e
0k
0r
0x
1~
0D
0`
1f
0&
b100 $
b100 )
b100 #
b100 (
b100 '
#45000
0N
0T
1M
1S
0Y
0L
0R
b1000 !
b1000 7
1Z
1O
1U
0J
0P
0W
07"
08"
0[
0A
0*
1V
0@
0?
b1000 6
19"
02"
0>"
04"
0@"
03"
0?"
05"
0A"
1+
0H
0d
0i
0v
0|
0#"
1>
1:"
1B"
1;"
1C"
1G
1c
b100 C
1j
1u
1{
b100 B
1$"
0F
1K
1Q
1X
0]
0b
0g
0n
0t
0z
0!"
0("
0."
1&
#50000
1F
1L
1R
1W
1]
1b
1g
1n
1t
1z
1!"
1("
1."
0w
0I
1r
1D
0&
b101 $
b101 )
b101 #
b101 (
b101 '
#55000
0M
b1010 !
b1010 7
1N
0K
0O
1J
b1010 6
17"
1A
0G
0u
1@
12"
1>"
13"
1?"
b101 C
1H
b101 B
1v
0E
1L
0R
0W
0]
0b
0g
0n
0s
0z
0!"
0("
0."
1&
#60000
1E
1K
1R
1W
1]
1b
1g
1n
1s
1z
1!"
1("
1."
1w
0}
1I
0e
0r
1x
0D
1`
0&
b110 $
b110 )
b110 #
b110 (
b110 '
#65000
0N
1M
0S
0L
b1100 !
b1100 7
1T
1O
0J
0Q
07"
0U
0A
1P
0@
b1100 6
18"
02"
0>"
03"
0?"
1*
0H
0c
0v
0{
1?
14"
1@"
15"
1A"
1G
b110 C
1d
1u
b110 B
1|
0F
1K
1R
0W
0]
0a
0g
0n
0t
0y
0!"
0("
0."
1&
#70000
1F
1L
1Q
1W
1]
1a
1g
1n
1t
1y
1!"
1("
1."
0w
0I
1r
1D
0&
b111 $
b111 )
b111 #
b111 (
b111 '
#75000
0M
b1110 !
b1110 7
1N
0K
0O
1J
b1110 6
17"
1A
0G
0u
1@
12"
1>"
13"
1?"
b111 C
1H
b111 B
1v
0E
1L
0Q
0W
0]
0a
0g
0n
0s
0y
0!"
0("
0."
1&
#80000
1E
1K
1Q
1W
1]
1a
1g
1n
1s
1y
1!"
1("
1."
1w
1}
1%"
0+"
1I
1e
1k
0q
0r
0x
0~
1&"
0D
0`
0f
1l
0&
b1000 $
b1000 )
b1000 #
b1000 (
b1000 '
#85000
0N
0T
b0 !
b0 7
0Z
1M
1S
1Y
0L
0R
0X
0^
1O
1U
1[
1"
0J
0P
0V
07"
08"
b0 6
09"
0\
0A
0*
0+
0_
0@
0?
0>
1,
02"
0>"
04"
0@"
0:"
0B"
03"
0?"
05"
0A"
0;"
0C"
0H
0d
0j
0o
0v
0|
0$"
0)"
1=
1<"
1D"
1="
1E"
1G
1c
1i
b1000 C
1p
1u
1{
1#"
b1000 B
1*"
0F
1K
1Q
1W
1]
0b
0h
0m
0t
0z
0""
0'"
0."
1&
#90000
1F
1L
1R
1X
1\
1b
1h
1m
1t
1z
1""
1'"
1."
0w
0I
1r
1D
0&
b1001 $
b1001 )
b1001 #
b1001 (
b1001 '
#95000
0M
b10 !
b10 7
1N
0K
0O
1J
b10 6
17"
1A
0G
0u
1@
12"
1>"
13"
1?"
b1001 C
1H
b1001 B
1v
0E
1L
0R
0X
0\
0b
0h
0m
0s
0z
0""
0'"
0."
1&
#100000
1E
1K
1R
1X
1\
1b
1h
1m
1s
1z
1""
1'"
1."
1w
0}
1I
0e
0r
1x
0D
1`
0&
b1010 $
b1010 )
b1010 #
b1010 (
b1010 '
#105000
0N
1M
0S
0L
b100 !
b100 7
1T
1O
0J
0Q
07"
0U
0A
1P
0@
b100 6
18"
02"
0>"
03"
0?"
1*
0H
0c
0v
0{
1?
14"
1@"
15"
1A"
1G
b1010 C
1d
1u
b1010 B
1|
0F
1K
1R
0X
0\
0a
0h
0m
0t
0y
0""
0'"
0."
1&
#110000
1F
1L
1Q
1X
1\
1a
1h
1m
1t
1y
1""
1'"
1."
0w
0I
1r
1D
0&
b1011 $
b1011 )
b1011 #
b1011 (
b1011 '
#115000
0M
b110 !
b110 7
1N
0K
0O
1J
b110 6
17"
1A
0G
0u
1@
12"
1>"
13"
1?"
b1011 C
1H
b1011 B
1v
0E
1L
0Q
0X
0\
0a
0h
0m
0s
0y
0""
0'"
0."
1&
#120000
1E
1K
1Q
1X
1\
1a
1h
1m
1s
1y
1""
1'"
1."
1w
1}
0%"
1I
1e
0k
0r
0x
1~
0D
0`
1f
0&
b1100 $
b1100 )
b1100 #
b1100 (
b1100 '
#125000
0N
0T
1M
1S
0Y
0L
0R
b1000 !
b1000 7
1Z
1O
1U
0J
0P
0W
07"
08"
0[
0A
0*
1V
0@
0?
b1000 6
19"
02"
0>"
04"
0@"
03"
0?"
05"
0A"
1+
0H
0d
0i
0v
0|
0#"
1>
1:"
1B"
1;"
1C"
1G
1c
b1100 C
1j
1u
1{
b1100 B
1$"
0F
1K
1Q
1X
0\
0b
0g
0m
0t
0z
0!"
0'"
0."
1&
#130000
1F
1L
1R
1W
1\
1b
1g
1m
1t
1z
1!"
1'"
1."
0w
0I
1r
1D
0&
b1101 $
b1101 )
b1101 #
b1101 (
b1101 '
#135000
0M
b1010 !
b1010 7
1N
0K
0O
1J
b1010 6
17"
1A
0G
0u
1@
12"
1>"
13"
1?"
b1101 C
1H
b1101 B
1v
0E
1L
0R
0W
0\
0b
0g
0m
0s
0z
0!"
0'"
0."
1&
#140000
1E
1K
1R
1W
1\
1b
1g
1m
1s
1z
1!"
1'"
1."
1w
0}
1I
0e
0r
1x
0D
1`
0&
b1110 $
b1110 )
b1110 #
b1110 (
b1110 '
#145000
0N
1M
0S
0L
b1100 !
b1100 7
1T
1O
0J
0Q
07"
0U
0A
1P
0@
b1100 6
18"
02"
0>"
03"
0?"
1*
0H
0c
0v
0{
1?
14"
1@"
15"
1A"
1G
b1110 C
1d
1u
b1110 B
1|
0F
1K
1R
0W
0\
0a
0g
0m
0t
0y
0!"
0'"
0."
1&
#150000
1F
1L
1Q
1W
1\
1a
1g
1m
1t
1y
1!"
1'"
1."
0w
0I
1r
1D
0&
b1111 $
b1111 )
b1111 #
b1111 (
b1111 '
#155000
0M
b1110 !
b1110 7
1N
0K
0O
1J
b1110 6
17"
1A
0G
0u
1@
12"
1>"
13"
1?"
b1111 C
1H
b1111 B
1v
0E
1L
0Q
0W
0\
0a
0g
0m
0s
0y
0!"
0'"
0."
1&
#160000
1E
1K
1Q
1W
1\
1a
1g
1m
1s
1y
1!"
1'"
1."
0&
b10000 '
